exporter/__init__.py
exporter/app.py
exporter/constants.py
exporter/exceptions.py
exporter/helper.py
exporter/manage.py
exporter/service.py
kdave-0.2.2.dist-info/METADATA
kdave-0.2.2.dist-info/WHEEL
kdave-0.2.2.dist-info/entry_points.txt
kdave-0.2.2.dist-info/top_level.txt
kdave-0.2.2.dist-info/RECORD
