Metadata-Version: 2.1
Name: kdave
Version: 0.2.2
Summary: Kubernetes deprecated API versions exporter CLI.
Home-page: https://github.com/wayfair-incubator/kdave
Author: Ahmed ElBakry
Author-email: aelbakry@wayfair.com
License: UNKNOWN
Platform: UNKNOWN
Classifier: Programming Language :: Python
Classifier: Programming Language :: Python :: 3
Classifier: Programming Language :: Python :: 3.6
Classifier: Programming Language :: Python :: 3.7
Classifier: Programming Language :: Python :: 3.8
Requires-Dist: kubernetes (==11.0.0)
Requires-Dist: Click (==8.0)
Requires-Dist: terminaltables (==3.1.0)
Requires-Dist: semver (==2.13.0)
Requires-Dist: Flask (==2.1.0)
Requires-Dist: itsdangerous (==2.0.1)
Requires-Dist: prometheus-client (==0.5.0)
Requires-Dist: gevent (==21.1.2)
